ws2812_gpt_lp/__init__.py
ws2812_gpt_lp/ws2812gptlp.py
ws2812_gpt_lp-0.1.7.dist-info/LICENSE
ws2812_gpt_lp-0.1.7.dist-info/METADATA
ws2812_gpt_lp-0.1.7.dist-info/WHEEL
ws2812_gpt_lp-0.1.7.dist-info/top_level.txt
ws2812_gpt_lp-0.1.7.dist-info/RECORD
