Metadata-Version: 2.1
Name: ws2812-gpt-lp
Version: 0.1.7
Summary: A library to control WS2812 LEDs using SPI on Orange Pi
Author-email: Laurent Pastor <l.pastor@free.fr>
License: MIT
Project-URL: Homepage, https://github.com/l-pastor/ws2812-gpt-lp
Keywords: ws2812,orangepi,neopixel,armbian,orange pi,raspberry pi
Classifier: Programming Language :: Python :: 3
Classifier: License :: OSI Approved :: MIT License
Classifier: Operating System :: OS Independent
Requires-Python: >=3.6
License-File: LICENSE
Requires-Dist: spidev
